{
  "id": "container-with-most-water",
  "name": "Container With Most Water",
  "difficulty": "Medium",
  "description": "<p>Given <code>n</code> non-negative integers <code>a1, a2, ..., an</code>, where each represents a point at coordinate <code>(i, ai)</code>. <code>n</code> vertical lines are drawn such that the two endpoints of the line <code>i</code> is at <code>(i, ai)</code> and <code>(i, 0)</code>.</p><p>Find two lines, which, together with the x-axis forms a container, such that the container contains the most water.</p><ul><li><b>Area Formula:</b> <code>min(height[i], height[j]) * (j - i)</code></li><li><b>Optimal Strategy:</b> Use two pointers starting at both ends and move the pointer pointing to the shorter line inward.</li></ul>",
  "tags": [
    "Array",
    "Two Pointers",
    "Greedy"
  ],
  "slots": [
    {
      "id": "heights",
      "type": "array",
      "label": "Heights",
      "display": "bar"
    },
    {
      "id": "vars",
      "type": "hashmap",
      "label": "State Variables"
    }
  ],
  "inputs": [
    {
      "label": "Heights Array (comma separated)",
      "default": "1,8,6,2,5,4,8,3,7",
      "placeholder": "e.g. 1,8,6,2,5"
    }
  ],
  "code": "class Playground {\n    async run(inputs) {\n        // Parse Input\n        const inputStr = inputs[0] || \"1,8,6,2,5,4,8,3,7\";\n        const heights = inputStr.split(',').map(num => parseInt(num.trim()));\n\n        // Initialize Visualizer Slots\n        await this.heights.init(heights);\n        await this.vars.init([]);\n\n        let left = 0;\n        let right = heights.length - 1;\n        let maxArea = 0;\n\n        this.vars.put(\"maxArea\", 0);\n        this.vars.put(\"left\", left);\n        this.vars.put(\"right\", right);\n\n        while (left < right) {\n            // Update State Visualization\n            this.vars.put(\"left\", left);\n            this.vars.put(\"right\", right);\n\n            const hLeft = heights[left];\n            const hRight = heights[right];\n            const width = right - left;\n            const minHeight = Math.min(hLeft, hRight);\n            const currentArea = minHeight * width;\n\n            this.vars.put(\"currentArea\", currentArea);\n            this.vars.put(\"width\", width);\n            this.vars.put(\"minHeight\", minHeight);\n\n            // Highlight the two bars forming the container\n            this.heights.highlight(left, \"#00e0ff\");\n            this.heights.highlight(right, \"#00e0ff\");\n\n            if (currentArea > maxArea) {\n                maxArea = currentArea;\n                this.vars.put(\"maxArea\", maxArea);\n                this.log(`New max area found: ${maxArea} (Min Height: ${minHeight} * Width: ${width})`);\n            } else {\n                this.log(`Current area: ${currentArea}. Max area remains: ${maxArea}`);\n            }\n\n            await this.await();\n\n            // Clear highlights before moving pointers\n            this.heights.highlight(left, null);\n            this.heights.highlight(right, null);\n\n            // Logic: Move the smaller pointer to potentially find a taller bar \n            // that offsets the loss in width.\n            if (hLeft < hRight) {\n                this.log(`Left height (${hLeft}) < Right height (${hRight}). Incrementing Left pointer.`);\n                left++;\n            } else {\n                this.log(`Right height (${hRight}) <= Left height (${hLeft}). Decrementing Right pointer.`);\n                right--;\n            }\n            \n            await this.await();\n        }\n\n        this.log(`Algorithm finished. Maximum water volume: ${maxArea}`);\n        return maxArea;\n    }\n}"
}